<?xml version="1.0"?>
<!--Generated with glade3 3.4.5 on Sat Jul 19 11:01:19 2008 -->
<interface>
  <object class="GtkAdjustment" id="adjustment1">
    <property name="upper">100</property>
    <property name="lower">30</property>
    <property name="page_increment">10</property>
    <property name="step_increment">1</property>
    <property name="page_size">10</property>
    <property name="value">50</property>
  </object>
  <object class="GtkAdjustment" id="adjustment2">
    <property name="upper">100</property>
    <property name="lower">40</property>
    <property name="page_increment">10</property>
    <property name="step_increment">1</property>
    <property name="page_size">10</property>
    <property name="value">55</property>
  </object>
  <object class="GtkAdjustment" id="adjustment3">
    <property name="upper">1000</property>
    <property name="lower">1</property>
    <property name="page_increment">10</property>
    <property name="step_increment">5</property>
    <property name="page_size">10</property>
    <property name="value">120</property>
  </object>
  <object class="GtkListStore" id="model1">
    <columns>
      <column type="gchararray"/>
    </columns>
    <data>
      <row>
        <col id="0">auto</col>
      </row>
      <row>
        <col id="0">1</col>
      </row>
      <row>
        <col id="0">2</col>
      </row>
      <row>
        <col id="0">3</col>
      </row>
      <row>
        <col id="0">4</col>
      </row>
      <row>
        <col id="0">5</col>
      </row>
      <row>
        <col id="0">6</col>
      </row>
      <row>
        <col id="0">7</col>
      </row>
      <row>
        <col id="0">full speed</col>
      </row>
    </data>
  </object>
  <object class="GtkListStore" id="model2">
    <columns>
      <column type="gchararray"/>
    </columns>
    <data>
      <row>
        <col id="0">auto</col>
      </row>
      <row>
        <col id="0">1</col>
      </row>
      <row>
        <col id="0">2</col>
      </row>
      <row>
        <col id="0">3</col>
      </row>
      <row>
        <col id="0">4</col>
      </row>
      <row>
        <col id="0">5</col>
      </row>
      <row>
        <col id="0">6</col>
      </row>
      <row>
        <col id="0">7</col>
      </row>
      <row>
        <col id="0">full speed</col>
      </row>
    </data>
  </object>
  <object class="GtkWindow" id="window">
    <property name="title" translatable="yes">ThinkPad Fan Control</property>
    <property name="resizable">False</property>
    <property name="window_position">GTK_WIN_POS_CENTER</property>
    <property name="icon">icon.png</property>
    <child>
      <object class="GtkVBox" id="vbox1">
        <property name="visible">True</property>
        <child>
          <object class="GtkNotebook" id="notebook1">
            <property name="visible">True</property>
            <property name="can_focus">True</property>
            <property name="show_border">False</property>
            <child>
              <object class="GtkTable" id="table1">
                <property name="visible">True</property>
                <property name="n_rows">3</property>
                <property name="n_columns">3</property>
                <property name="column_spacing">10</property>
                <property name="row_spacing">10</property>
                <child>
                  <placeholder/>
                </child>
                <child>
                  <placeholder/>
                </child>
                <child>
                  <placeholder/>
                </child>
                <child>
                  <placeholder/>
                </child>
                <child>
                  <placeholder/>
                </child>
                <child>
                  <placeholder/>
                </child>
                <child>
                  <placeholder/>
                </child>
                <child>
                  <placeholder/>
                </child>
                <child>
                  <object class="GtkVBox" id="vbox2">
                    <property name="visible">True</property>
                    <child>
                      <object class="GtkLabel" id="optionsLabel">
                        <property name="visible">True</property>
                        <property name="label" translatable="yes">Current options: 120, 55, 50, full-speed</property>
                      </object>
                    </child>
                    <child>
                      <object class="GtkTable" id="table3">
                        <property name="visible">True</property>
                        <property name="n_rows">5</property>
                        <property name="n_columns">3</property>
                        <property name="column_spacing">10</property>
                        <property name="homogeneous">True</property>
                        <child>
                          <placeholder/>
                        </child>
                        <child>
                          <placeholder/>
                        </child>
                        <child>
                          <object class="GtkComboBox" id="autoSpeed">
                            <property name="visible">True</property>
                            <property name="model">model1</property>
                            <child>
                              <object class="GtkCellRendererText" id="renderer1"/>
                              <attributes>
                                <attribute name="text">0</attribute>
                              </attributes>
                            </child>
                          </object>
                          <packing>
                            <property name="left_attach">2</property>
                            <property name="right_attach">3</property>
                            <property name="top_attach">3</property>
                            <property name="bottom_attach">4</property>
                            <property name="y_options"/>
                          </packing>
                        </child>
                        <child>
                          <object class="GtkLabel" id="label7">
                            <property name="visible">True</property>
                            <property name="label" translatable="yes">Use this speed when temperature is critical:</property>
                          </object>
                          <packing>
                            <property name="right_attach">2</property>
                            <property name="top_attach">3</property>
                            <property name="bottom_attach">4</property>
                          </packing>
                        </child>
                        <child>
                          <object class="GtkSpinButton" id="safe">
                            <property name="visible">True</property>
                            <property name="can_focus">True</property>
                            <property name="adjustment">adjustment1</property>
                          </object>
                          <packing>
                            <property name="left_attach">2</property>
                            <property name="right_attach">3</property>
                            <property name="top_attach">2</property>
                            <property name="bottom_attach">3</property>
                            <property name="x_options"/>
                            <property name="y_options"/>
                          </packing>
                        </child>
                        <child>
                          <object class="GtkSpinButton" id="critical">
                            <property name="visible">True</property>
                            <property name="can_focus">True</property>
                            <property name="adjustment">adjustment2</property>
                          </object>
                          <packing>
                            <property name="left_attach">2</property>
                            <property name="right_attach">3</property>
                            <property name="top_attach">1</property>
                            <property name="bottom_attach">2</property>
                            <property name="x_options"/>
                            <property name="y_options"/>
                          </packing>
                        </child>
                        <child>
                          <object class="GtkSpinButton" id="sleep">
                            <property name="visible">True</property>
                            <property name="can_focus">True</property>
                            <property name="adjustment">adjustment3</property>
                          </object>
                          <packing>
                            <property name="left_attach">2</property>
                            <property name="right_attach">3</property>
                            <property name="x_options"/>
                            <property name="y_options"/>
                          </packing>
                        </child>
                        <child>
                          <object class="GtkLabel" id="label6">
                            <property name="visible">True</property>
                            <property name="label" translatable="yes">Sleep time:</property>
                          </object>
                          <packing>
                            <property name="right_attach">2</property>
                            <property name="x_options">GTK_FILL</property>
                            <property name="y_options"/>
                          </packing>
                        </child>
                        <child>
                          <object class="GtkLabel" id="label5">
                            <property name="visible">True</property>
                            <property name="label" translatable="yes">Critical temperature:</property>
                          </object>
                          <packing>
                            <property name="right_attach">2</property>
                            <property name="top_attach">1</property>
                            <property name="bottom_attach">2</property>
                            <property name="x_options">GTK_FILL</property>
                            <property name="y_options"/>
                          </packing>
                        </child>
                        <child>
                          <object class="GtkLabel" id="label9">
                            <property name="visible">True</property>
                            <property name="label" translatable="yes">Safe temperature:</property>
                          </object>
                          <packing>
                            <property name="right_attach">2</property>
                            <property name="top_attach">2</property>
                            <property name="bottom_attach">3</property>
                            <property name="x_options">GTK_FILL</property>
                            <property name="y_options"/>
                          </packing>
                        </child>
                        <child>
                          <object class="GtkButton" id="run">
                            <property name="visible">True</property>
                            <property name="can_focus">True</property>
                            <property name="has_focus">True</property>
                            <property name="receives_default">True</property>
                            <property name="label" translatable="yes">Change options</property>
                          </object>
                          <packing>
                            <property name="left_attach">1</property>
                            <property name="right_attach">2</property>
                            <property name="top_attach">4</property>
                            <property name="bottom_attach">5</property>
                            <property name="y_options"/>
                          </packing>
                        </child>
                      </object>
                      <packing>
                        <property name="position">1</property>
                      </packing>
                    </child>
                  </object>
                  <packing>
                    <property name="left_attach">1</property>
                    <property name="right_attach">2</property>
                    <property name="top_attach">1</property>
                    <property name="bottom_attach">2</property>
                  </packing>
                </child>
              </object>
            </child>
            <child type="tab">
              <object class="GtkLabel" id="label2">
                <property name="visible">True</property>
                <property name="label" translatable="yes">Automatic control</property>
              </object>
              <packing>
                <property name="tab_fill">False</property>
              </packing>
            </child>
            <child>
              <object class="GtkTable" id="table2">
                <property name="visible">True</property>
                <property name="n_rows">1</property>
                <property name="n_columns">3</property>
                <child>
                  <object class="GtkButton" id="speedButton">
                    <property name="visible">True</property>
                    <property name="can_focus">True</property>
                    <property name="receives_default">True</property>
                    <property name="label" translatable="yes">Change speed</property>
                  </object>
                  <packing>
                    <property name="left_attach">2</property>
                    <property name="right_attach">3</property>
                    <property name="x_options">GTK_EXPAND</property>
                    <property name="y_options"/>
                  </packing>
                </child>
                <child>
                  <object class="GtkLabel" id="label4">
                    <property name="visible">True</property>
                    <property name="label" translatable="yes">Choose speed:</property>
                  </object>
                  <packing>
                    <property name="y_options">GTK_EXPAND</property>
                  </packing>
                </child>
                <child>
                  <object class="GtkComboBox" id="speed">
                    <property name="visible">True</property>
                    <property name="model">model2</property>
                    <child>
                      <object class="GtkCellRendererText" id="renderer2"/>
                      <attributes>
                        <attribute name="text">0</attribute>
                      </attributes>
                    </child>
                  </object>
                  <packing>
                    <property name="left_attach">1</property>
                    <property name="right_attach">2</property>
                    <property name="y_options"/>
                  </packing>
                </child>
              </object>
              <packing>
                <property name="position">1</property>
                <property name="tab_fill">False</property>
              </packing>
            </child>
            <child type="tab">
              <object class="GtkLabel" id="label3">
                <property name="visible">True</property>
                <property name="label" translatable="yes">Manual control</property>
              </object>
              <packing>
                <property name="position">1</property>
                <property name="tab_fill">False</property>
              </packing>
            </child>
            <child>
              <object class="GtkTable" id="table4">
                <property name="visible">True</property>
                <property name="n_rows">3</property>
                <property name="n_columns">3</property>
                <property name="column_spacing">10</property>
                <property name="row_spacing">10</property>
                <child>
                  <placeholder/>
                </child>
                <child>
                  <placeholder/>
                </child>
                <child>
                  <placeholder/>
                </child>
                <child>
                  <placeholder/>
                </child>
                <child>
                  <placeholder/>
                </child>
                <child>
                  <placeholder/>
                </child>
                <child>
                  <placeholder/>
                </child>
                <child>
                  <placeholder/>
                </child>
                <child>
                  <object class="GtkVBox" id="vbox4">
                    <property name="visible">True</property>
                    <child>
                      <object class="GtkImage" id="image1">
                        <property name="visible">True</property>
                        <property name="pixbuf">logo.png</property>
                      </object>
                    </child>
                    <child>
                      <object class="GtkLabel" id="label1">
                        <property name="visible">True</property>
                        <property name="label" translatable="yes">V0.5
Written by Stanko Tadi&#x107;
Copyright &#xA9; 2008 Stanko Tadi&#x107;</property>
                        <property name="justify">GTK_JUSTIFY_CENTER</property>
                      </object>
                      <packing>
                        <property name="padding">10</property>
                        <property name="position">1</property>
                      </packing>
                    </child>
                    <child>
                      <object class="GtkLabel" id="label10">
                        <property name="visible">True</property>
                        <property name="label" translatable="yes">http://stanko.mfhinc.net/projects.php</property>
                      </object>
                      <packing>
                        <property name="position">2</property>
                      </packing>
                    </child>
                  </object>
                  <packing>
                    <property name="left_attach">1</property>
                    <property name="right_attach">2</property>
                    <property name="top_attach">1</property>
                    <property name="bottom_attach">2</property>
                  </packing>
                </child>
              </object>
            </child>
            <child type="tab">
              <object class="GtkLabel" id="label8">
                <property name="visible">True</property>
                <property name="label" translatable="yes">About</property>
              </object>
              <packing>
                <property name="position">2</property>
                <property name="tab_fill">False</property>
              </packing>
            </child>
          </object>
          <packing>
            <property name="expand">False</property>
            <property name="fill">False</property>
          </packing>
        </child>
        <child>
          <object class="GtkVBox" id="vbox3">
            <property name="visible">True</property>
            <child>
              <object class="GtkLabel" id="level">
                <property name="visible">True</property>
                <property name="label" translatable="yes">Fans level - auto</property>
                <property name="justify">GTK_JUSTIFY_CENTER</property>
              </object>
              <packing>
                <property name="padding">3</property>
              </packing>
            </child>
            <child>
              <object class="GtkLabel" id="log">
                <property name="visible">True</property>
                <property name="label" translatable="yes">WELCOME!
This is fan control program for IBM/Lenovo ThinkPads</property>
                <property name="justify">GTK_JUSTIFY_CENTER</property>
              </object>
              <packing>
                <property name="padding">5</property>
                <property name="position">1</property>
              </packing>
            </child>
            <child>
              <object class="GtkHButtonBox" id="hbuttonbox2">
                <property name="visible">True</property>
                <property name="layout_style">GTK_BUTTONBOX_SPREAD</property>
                <child>
                  <object class="GtkButton" id="hide">
                    <property name="visible">True</property>
                    <property name="can_focus">True</property>
                    <property name="receives_default">True</property>
                    <property name="label" translatable="yes">To tray</property>
                  </object>
                </child>
                <child>
                  <object class="GtkButton" id="exit">
                    <property name="visible">True</property>
                    <property name="can_focus">True</property>
                    <property name="receives_default">True</property>
                    <property name="label" translatable="yes">Exit</property>
                  </object>
                  <packing>
                    <property name="position">1</property>
                  </packing>
                </child>
              </object>
              <packing>
                <property name="padding">3</property>
                <property name="position">2</property>
              </packing>
            </child>
            <child>
              <object class="GtkStatusbar" id="statusbar">
                <property name="visible">True</property>
                <property name="spacing">2</property>
              </object>
              <packing>
                <property name="expand">False</property>
                <property name="position">3</property>
              </packing>
            </child>
          </object>
          <packing>
            <property name="expand">False</property>
            <property name="fill">False</property>
            <property name="position">1</property>
          </packing>
        </child>
      </object>
    </child>
  </object>
</interface>
